appli_django/__init__.py
appli_django/cli.py
appli_django/main.py
appli_django-0.3.0.dist-info/METADATA
appli_django-0.3.0.dist-info/WHEEL
appli_django-0.3.0.dist-info/entry_points.txt
appli_django-0.3.0.dist-info/top_level.txt
appli_django-0.3.0.dist-info/RECORD
