Metadata-Version: 2.4
Name: appli-django
Version: 0.3.0
Summary: Créer rapidement une structure complète d'application Django.
Author: Nicosidick
License: MIT
Requires-Python: >=3.6
Dynamic: author
Dynamic: description
Dynamic: description-content-type
Dynamic: license
Dynamic: requires-python
Dynamic: summary
